ansnp
