Metadata-Version: 2.4
Name: ansnp
Version: 0.1.0.post3
Summary: A Python package with C++ extensions using pybind11 developed by Zhihao Duan
Home-page: https://github.com/duanzhiihao/ans-numpy/
Author: Zhihao Duan
Author-email: duan90@purdue.edu
Maintainer: Wei Jiang
Maintainer-email: jiangwei@stu.pku.edu.cn
Classifier: Development Status :: 3 - Alpha
Classifier: Intended Audience :: Developers
Classifier: License :: OSI Approved :: MIT License
Classifier: Programming Language :: Python :: 3
Classifier: Programming Language :: Python :: 3.6
Classifier: Programming Language :: Python :: 3.7
Classifier: Programming Language :: Python :: 3.8
Classifier: Programming Language :: Python :: 3.9
Classifier: Programming Language :: Python :: 3.10
Classifier: Programming Language :: Python :: 3.11
Classifier: Programming Language :: C++
Requires-Python: >=3.10
Requires-Dist: pybind11>=2.6.0
Dynamic: author
Dynamic: author-email
Dynamic: maintainer
Dynamic: maintainer-email
Dynamic: summary
